fastapi_boiler/__init__.py
fastapi_boiler/create_app.py
fastapi_boiler/fastapi_boilerplate/.gitignore
fastapi_boiler/fastapi_boilerplate/Dockerfile
fastapi_boiler/fastapi_boilerplate/README.md
fastapi_boiler/fastapi_boilerplate/app/__init__.py
fastapi_boiler/fastapi_boilerplate/app/v1/__init__.py
fastapi_boiler/fastapi_boilerplate/app/v1/health/__init__.py
fastapi_boiler/fastapi_boilerplate/app/v1/health/router.py
fastapi_boiler/fastapi_boilerplate/app/views.py
fastapi_boiler/fastapi_boilerplate/core/__init__.py
fastapi_boiler/fastapi_boilerplate/core/database.py
fastapi_boiler/fastapi_boilerplate/core/exception_handlers.py
fastapi_boiler/fastapi_boilerplate/core/exceptions.py
fastapi_boiler/fastapi_boilerplate/core/extensions.py
fastapi_boiler/fastapi_boilerplate/core/factory.py
fastapi_boiler/fastapi_boilerplate/core/middlewares.py
fastapi_boiler/fastapi_boilerplate/docker-compose.yml
fastapi_boiler/fastapi_boilerplate/pyproject.toml
fastapi_boiler/fastapi_boilerplate/requirements.txt
fastapi_boiler/fastapi_boilerplate/server.py
fastapi_boiler/fastapi_boilerplate/settings/__init__.py
fastapi_boiler/fastapi_boilerplate/settings/config.py
fastapi_boiler/fastapi_boilerplate/tests/__init__.py
fastapi_boiler/fastapi_boilerplate/tests/conftest.py
fastapi_boiler/fastapi_boilerplate/tests/routers/__init__.py
fastapi_boiler/fastapi_boilerplate/tests/routers/test_health.py
fastapi_boiler-0.1.4.dist-info/METADATA
fastapi_boiler-0.1.4.dist-info/WHEEL
fastapi_boiler-0.1.4.dist-info/entry_points.txt
fastapi_boiler-0.1.4.dist-info/RECORD
