Metadata-Version: 2.1
Name: fastapi-boiler
Version: 0.1.4
Summary: This is a boilerplate project for building a web application using FastAPI
Author: Ali Heydarli
Author-email: ali.heyderli@gmail.com
Requires-Python: >=3.11,<4.0
Classifier: Programming Language :: Python :: 3
Classifier: Programming Language :: Python :: 3.11
Requires-Dist: click (>=8.0.0,<9.0.0)
